{
	"books" : [
		{
		"Title": "The Great Gatsby",
		"Author": "F.Scott Fitzerald",
		"Genre": "Historical Fiction",
		"Published":"1925"
		},
		{
		"Title": "1984",
		"Author": "George Orwell",
		"Genre": "Dystopian",
		"Published":"1949"
		},
		{
		"Title": "Fight Club",
		"Author": "Chuck Palahniuk",
		"Genre": "Novel,
		"Published":"1925"
		},
		{
		"Title": "The Tailsman"
		"Author": "Stephen King and Peter Straub"
		"Genre": "Horror Fiction"
		"Published": "1984"
		}
    ]
}

		

	